VividText/__init__.py
vividtext-0.3.3.dist-info/licenses/LICENSE
vividtext-0.3.3.dist-info/METADATA
vividtext-0.3.3.dist-info/WHEEL
vividtext-0.3.3.dist-info/top_level.txt
vividtext-0.3.3.dist-info/RECORD
